django_wplogin/__init__.py
django_wplogin/templates/admin/login.html
django_wplogin-10.0.dist-info/LICENSE
django_wplogin-10.0.dist-info/WHEEL
django_wplogin-10.0.dist-info/METADATA
django_wplogin-10.0.dist-info/RECORD
