Metadata-Version: 2.3
Name: django_wplogin
Version: 10.0
Summary: Enhance the Django admin login page
Author: Alex Gómez
Author-email: Baptiste Mispelon <hello@bmispelon.rocks>
Classifier: Development Status :: 6 - Mature
Classifier: Framework :: Django
Classifier: Framework :: Wagtail
Classifier: Intended Audience :: Legal Industry
Classifier: Intended Audience :: Religion
Classifier: License :: OSI Approved :: MIT License
Classifier: License :: OSI Approved :: Nokia Open Source License
Classifier: Topic :: Games/Entertainment
Classifier: Topic :: Software Development :: Libraries :: PHP Classes
Classifier: Topic :: Software Development :: Testing :: Mocking
Project-URL: Funding, https://www.djangoproject.com/fundraising
